examples/__init__.py
examples/create_test_data.py
examples/higgs.py
examples/higgs_parquet.py
examples/readme.py
examples/readme_sklearn_api.py
examples/simple.py
examples/simple_dask.py
examples/simple_modin.py
examples/simple_predict.py
examples/simple_ray_dataset.py
examples/simple_tune.py
examples/train_on_test_data.py
examples/train_with_ml_dataset.py
lightgbm_ray/__init__.py
lightgbm_ray/callback.py
lightgbm_ray/main.py
lightgbm_ray/sklearn.py
lightgbm_ray/tune.py
lightgbm_ray/util.py
lightgbm_ray/examples/__init__.py
lightgbm_ray/examples/create_test_data.py
lightgbm_ray/examples/higgs.py
lightgbm_ray/examples/higgs_parquet.py
lightgbm_ray/examples/readme.py
lightgbm_ray/examples/readme_sklearn_api.py
lightgbm_ray/examples/simple.py
lightgbm_ray/examples/simple_dask.py
lightgbm_ray/examples/simple_modin.py
lightgbm_ray/examples/simple_predict.py
lightgbm_ray/examples/simple_ray_dataset.py
lightgbm_ray/examples/simple_tune.py
lightgbm_ray/examples/train_on_test_data.py
lightgbm_ray/examples/train_with_ml_dataset.py
lightgbm_ray/tests/__init__.py
lightgbm_ray/tests/test_client.py
lightgbm_ray/tests/test_end_to_end.py
lightgbm_ray/tests/test_fault_tolerance.py
lightgbm_ray/tests/test_lightgbm.py
lightgbm_ray/tests/test_lightgbm_api.py
lightgbm_ray/tests/test_tune.py
lightgbm_ray-0.1.9.dist-info/LICENSE
lightgbm_ray-0.1.9.dist-info/METADATA
lightgbm_ray-0.1.9.dist-info/WHEEL
lightgbm_ray-0.1.9.dist-info/top_level.txt
lightgbm_ray-0.1.9.dist-info/RECORD
