Metadata-Version: 2.1
Name: lightgbm-ray
Version: 0.1.9
Summary: A Ray backend for distributed LightGBM
Home-page: https://github.com/ray-project/lightgbm_ray
Author: Ray Team
Author-email: UNKNOWN
License: Apache 2.0
Platform: UNKNOWN
Requires-Dist: lightgbm (>=3.2.1)
Requires-Dist: xgboost-ray (>=0.1.12)
Requires-Dist: packaging
